logisticRegressionScratch/__init__.py
logisticRegressionScratch/main.py
logitsyug-2025.0.0.dist-info/METADATA
logitsyug-2025.0.0.dist-info/WHEEL
logitsyug-2025.0.0.dist-info/top_level.txt
logitsyug-2025.0.0.dist-info/RECORD
